manish_pype_pakage/__init__.py
manish_pype_pakage/sigmoid_function.py
manish_pype_pakage/softmax.py
manish_pype_pakage-0.2.0.dist-info/METADATA
manish_pype_pakage-0.2.0.dist-info/WHEEL
manish_pype_pakage-0.2.0.dist-info/top_level.txt
manish_pype_pakage-0.2.0.dist-info/RECORD
