Metadata-Version: 2.1
Name: manish-pype-pakage
Version: 0.2.0
Summary: A simple python pakage for softmax function
Author: manish
Classifier: Programming Language :: Python :: 3
Classifier: License :: OSI Approved :: MIT License
Classifier: Operating System :: OS Independent
Requires-Python: >=3.7
Requires-Dist: numpy>=1.21.0
